breakout_env/__init__.py
breakout_env/breakout_env.py
breakout_env/assets/0.npy
breakout_env/assets/1.npy
breakout_env/assets/2.npy
breakout_env/assets/3.npy
breakout_env/assets/4.npy
breakout_env/assets/5.npy
breakout_env/assets/6.npy
breakout_env/assets/7.npy
breakout_env/assets/8.npy
breakout_env/assets/9.npy
breakout_env/assets/base.npy
breakout_env-1.0.5.dist-info/DESCRIPTION.rst
breakout_env-1.0.5.dist-info/METADATA
breakout_env-1.0.5.dist-info/RECORD
breakout_env-1.0.5.dist-info/WHEEL
breakout_env-1.0.5.dist-info/metadata.json
breakout_env-1.0.5.dist-info/top_level.txt
