Metadata-Version: 2.0
Name: breakout-env
Version: 1.0.5
Summary: A configurable Breakout environment for reinforcement learning
Home-page: https://github.com/SSARCandy/breakout-env
Author: SSARCandy
Author-email: ssarcandy@gmail.com
License: MIT
Requires-Dist: distribute
Requires-Dist: numpy (>=1.1)
